zendesk_exporter/__init__.py
zendesk_exporter/export_tickets.py
zendesk_exporter-0.0.32.dist-info/METADATA
zendesk_exporter-0.0.32.dist-info/RECORD
zendesk_exporter-0.0.32.dist-info/WHEEL
zendesk_exporter-0.0.32.dist-info/entry_points.txt
zendesk_exporter-0.0.32.dist-info/top_level.txt
