Metadata-Version: 2.1
Name: zendesk-exporter
Version: 0.0.32
Summary: A small zendesk export tool
Home-page: https://github.com/markhalonen/zendesk_exporter
Author: Mark Halonen
Author-email: halonen.mark@gmail.com
License: UNKNOWN
Platform: UNKNOWN
Classifier: Programming Language :: Python :: 2
Classifier: License :: OSI Approved :: MIT License
Classifier: Operating System :: OS Independent
Requires-Dist: openpyxl
Requires-Dist: requests
